b2h5py/__init__.py
b2h5py/auto.py
b2h5py/blosc2.py
b2h5py/patch.py
b2h5py/tests/__init__.py
b2h5py/tests/common.py
b2h5py/tests/test_b2dataset.py
b2h5py/tests/test_dataset_patching.py
b2h5py/tests/test_patched_h5py.py
b2h5py/tests/test_slicing_blosc2.py
b2h5py-0.5.1.dist-info/licenses/LICENSE
b2h5py-0.5.1.dist-info/METADATA
b2h5py-0.5.1.dist-info/WHEEL
b2h5py-0.5.1.dist-info/top_level.txt
b2h5py-0.5.1.dist-info/RECORD
