Metadata-Version: 2.4
Name: b2h5py
Version: 0.5.1
Summary: Transparent optimized reading of n-dimensional Blosc2 slices for h5py
Author-email: Blosc Development Team <blosc@blosc.org>
License: Copyright (c) 2023 The Blosc Development Team <blosc@blosc.org>
Project-URL: Homepage, https://github.com/Blosc/b2h5py
Project-URL: Issues, https://github.com/Blosc/b2h5py/issues
Keywords: h5py,HDF5,Blosc2
Classifier: Development Status :: 4 - Beta
Classifier: Intended Audience :: Developers
Classifier: Intended Audience :: Information Technology
Classifier: Intended Audience :: Science/Research
Classifier: License :: OSI Approved :: BSD License
Classifier: Programming Language :: Python
Classifier: Programming Language :: Python :: 3
Classifier: Programming Language :: Python :: 3 :: Only
Classifier: Topic :: Database
Classifier: Topic :: Scientific/Engineering
Classifier: Topic :: Software Development :: Libraries :: Python Modules
Requires-Python: >=3.3
License-File: LICENSE
Requires-Dist: blosc2>=2.3.0
Requires-Dist: numpy
Requires-Dist: h5py>=3.0
Requires-Dist: hdf5plugin>=4.3.0
Provides-Extra: h5py-test
Requires-Dist: pytest; extra == "h5py-test"
Dynamic: license-file
